coconut/__init__.py
coconut/proofs.py
coconut/scheme.py
coconut/utils.py
coconut_lib-1.3.1.dist-info/LICENSE
coconut_lib-1.3.1.dist-info/METADATA
coconut_lib-1.3.1.dist-info/WHEEL
coconut_lib-1.3.1.dist-info/top_level.txt
coconut_lib-1.3.1.dist-info/RECORD
