Metadata-Version: 2.1
Name: coconut-lib
Version: 1.3.1
Summary: Threshold Issuance Selective Disclosure Credentials.
Home-page: https://pypi.org/project/coconut-lib
Author: Alberto Sonnino
Author-email: alberto.sonnino@ucl.ac.uk
License: UNKNOWN
Project-URL: Paper, https://arxiv.org/abs/1802.07344
Project-URL: Bug Reports, https://github.com/asonnino/coconut
Project-URL: Funding, https://www.decodeproject.eu
Project-URL: Source, https://github.com/asonnino/coconut
Keywords: anonymous-credentials threshold-cryptography blockchains distributed-ledgers
Platform: UNKNOWN
Classifier: Development Status :: 4 - Beta
Classifier: Intended Audience :: Science/Research
Classifier: Topic :: Security :: Cryptography
Classifier: License :: OSI Approved :: BSD License
Classifier: Programming Language :: Python :: 2.7
Classifier: Programming Language :: Python :: 3.5
Requires-Dist: petlib
Requires-Dist: bplib
